[
    {
        "best_fitness": 1.1785299569439318,
        "mean_fitness": 0.6493821096653535
    },
    {
        "best_fitness": 1.1986039776087523,
        "mean_fitness": 0.6087249021852025
    },
    {
        "best_fitness": 1.1491893236523256,
        "mean_fitness": 0.650513945068877
    },
    {
        "best_fitness": 0.9485371410638788,
        "mean_fitness": 0.20276567176063645
    },
    {
        "best_fitness": 1.1289641282604492,
        "mean_fitness": 0.5904677126014615
    },
    {
        "best_fitness": 1.0755398376379834,
        "mean_fitness": 0.5957401358798013
    },
    {
        "best_fitness": 0.9019307792520244,
        "mean_fitness": 0.47074366043387816
    },
    {
        "best_fitness": 1.0613493990195972,
        "mean_fitness": 0.5994604762066739
    },
    {
        "best_fitness": 0.9019307792520244,
        "mean_fitness": 0.5036053682555074
    },
    {
        "best_fitness": 0.9019307792520244,
        "mean_fitness": 0.4611291743667305
    },
    {
        "best_fitness": 0.8645876555789769,
        "mean_fitness": 0.40092606162199307
    },
    {
        "best_fitness": 1.0613493990195972,
        "mean_fitness": 0.3634850565814598
    },
    {
        "best_fitness": 1.0613493990195972,
        "mean_fitness": 0.4476499408609745
    },
    {
        "best_fitness": 1.0613493990195972,
        "mean_fitness": 0.45364414225136596
    },
    {
        "best_fitness": 0.7699633376109858,
        "mean_fitness": 0.044264377171243485
    },
    {
        "best_fitness": 0.7700782493055672,
        "mean_fitness": 0.5313387037559626
    },
    {
        "best_fitness": 0.7885975292744694,
        "mean_fitness": 0.43488136634895974
    },
    {
        "best_fitness": 0.6890818985208472,
        "mean_fitness": 0.3436813447153442
    },
    {
        "best_fitness": 0.7649739371164584,
        "mean_fitness": 0.49377341622654425
    },
    {
        "best_fitness": 0.8256834331827688,
        "mean_fitness": 0.7496670007248721
    },
    {
        "best_fitness": -0.1526487851242491,
        "mean_fitness": -0.18067353616459356
    },
    {
        "best_fitness": 0.7451290282587831,
        "mean_fitness": 0.7024256344899024
    },
    {
        "best_fitness": -0.39286468177341344,
        "mean_fitness": -0.4423621280615366
    },
    {
        "best_fitness": 0.8645876555789769,
        "mean_fitness": 0.8645876555789769
    },
    {
        "best_fitness": 0.7291167483861226,
        "mean_fitness": 0.39815573219172
    },
    {
        "best_fitness": 0.5842757369816967,
        "mean_fitness": -0.05860084249327896
    },
    {
        "best_fitness": 0.6937526264165187,
        "mean_fitness": 0.27788728015142544
    }
]