[
    {
        "best_fitness": 0.8949138839236729,
        "mean_fitness": 0.3110651541869221
    },
    {
        "best_fitness": 0.8248460651699537,
        "mean_fitness": 0.289496684506113
    },
    {
        "best_fitness": 0.7471027707134928,
        "mean_fitness": 0.3225809142772151
    },
    {
        "best_fitness": 0.6743027756120552,
        "mean_fitness": 0.3414417991852155
    },
    {
        "best_fitness": 0.7799754208118959,
        "mean_fitness": 0.25328221224221775
    },
    {
        "best_fitness": 0.6115275549401872,
        "mean_fitness": 0.38588244382156356
    },
    {
        "best_fitness": 0.5650996721207155,
        "mean_fitness": 0.295416555491868
    },
    {
        "best_fitness": 0.6758333066551084,
        "mean_fitness": 0.24389074043802597
    },
    {
        "best_fitness": 0.6470915567186032,
        "mean_fitness": 0.24696747123887086
    },
    {
        "best_fitness": 0.5436137844629234,
        "mean_fitness": 0.45742569834773883
    }
]