[
    {
        "best_fitness": 0.8740952854329144,
        "mean_fitness": 0.2713023656498436
    },
    {
        "best_fitness": 0.7629056292939552,
        "mean_fitness": 0.37023702296929223
    },
    {
        "best_fitness": 0.8647614123000695,
        "mean_fitness": 0.35012556075713325
    },
    {
        "best_fitness": 0.5773153122199002,
        "mean_fitness": 0.37641698920961025
    },
    {
        "best_fitness": 0.5895834517367535,
        "mean_fitness": 0.36858284683014614
    },
    {
        "best_fitness": 0.6525357101876321,
        "mean_fitness": 0.32781346789439453
    },
    {
        "best_fitness": 0.6428847734080793,
        "mean_fitness": 0.3597111008646863
    },
    {
        "best_fitness": 0.6140129589837715,
        "mean_fitness": 0.3322974345139203
    },
    {
        "best_fitness": 0.6674396455071391,
        "mean_fitness": 0.3399246463546816
    },
    {
        "best_fitness": 0.5588015792709035,
        "mean_fitness": 0.35838974762895465
    },
    {
        "best_fitness": 0.5507267109912423,
        "mean_fitness": 0.3320533928711184
    },
    {
        "best_fitness": 0.5358323411291863,
        "mean_fitness": 0.3690298023147647
    },
    {
        "best_fitness": 0.4992429870667825,
        "mean_fitness": 0.4992429870667825
    },
    {
        "best_fitness": 0.5495919805717895,
        "mean_fitness": 0.17453654996924203
    },
    {
        "best_fitness": 0.5313712640996028,
        "mean_fitness": 0.42433323681121327
    },
    {
        "best_fitness": 0.47136241810161716,
        "mean_fitness": 0.463864592206348
    }
]