{
  "nodes": {
    "0": "input",
    "1": "input",
    "2": "input",
    "3": "input",
    "4": "input",
    "5": "input",
    "6": "input",
    "7": "input",
    "8": "input",
    "9": "input",
    "10": "input",
    "11": "input",
    "12": "input",
    "13": "input",
    "14": "input",
    "15": "input",
    "16": "input",
    "17": "input",
    "18": "input",
    "19": "input",
    "20": "input",
    "21": "input",
    "22": "input",
    "23": "input",
    "24": "input",
    "25": "input",
    "26": "input",
    "27": "output",
    "28": "output",
    "29": "output",
    "30": "output",
    "31": "output",
    "32": "output",
    "33": "output",
    "34": "output",
    "35": "output",
    "36": "output",
    "37": "output",
    "38": "output",
    "39": "hidden",
    "40": "hidden",
    "41": "hidden",
    "42": "hidden",
    "43": "hidden",
    "45": "hidden",
    "46": "hidden"
  },
  "connections": {
    "18,28": {
      "weight": 8.436255037292398,
      "enabled": true
    },
    "17,32": {
      "weight": -3.928232161951322,
      "enabled": true
    },
    "7,36": {
      "weight": -6.933683130578453,
      "enabled": false
    },
    "18,38": {
      "weight": -7.96639690694742,
      "enabled": false
    },
    "0,29": {
      "weight": 5.904844007691244,
      "enabled": true
    },
    "10,34": {
      "weight": 0.4093330187461355,
      "enabled": false
    },
    "18,39": {
      "weight": 9.852039130198783,
      "enabled": true
    },
    "39,38": {
      "weight": 7.633122495800237,
      "enabled": true
    },
    "10,40": {
      "weight": 0.4093330187461355,
      "enabled": false
    },
    "40,34": {
      "weight": 4.015349786551976,
      "enabled": true
    },
    "13,39": {
      "weight": 2.4122863744325027,
      "enabled": true
    },
    "13,34": {
      "weight": -0.854729643812167,
      "enabled": true
    },
    "8,34": {
      "weight": 5.564000748602735,
      "enabled": true
    },
    "26,30": {
      "weight": -5.042366871845272,
      "enabled": true
    },
    "10,41": {
      "weight": 8.727403506816845,
      "enabled": true
    },
    "41,40": {
      "weight": 10.388277117544835,
      "enabled": true
    },
    "1,32": {
      "weight": 0.8187360238974359,
      "enabled": true
    },
    "7,30": {
      "weight": 0.3525816076640238,
      "enabled": true
    },
    "8,28": {
      "weight": -0.7173257796214003,
      "enabled": true
    },
    "17,33": {
      "weight": 3.3363545681562794,
      "enabled": true
    },
    "20,29": {
      "weight": 1.5237186693200755,
      "enabled": true
    },
    "11,28": {
      "weight": -0.24274027764543504,
      "enabled": false
    },
    "14,41": {
      "weight": 7.78840765032942,
      "enabled": true
    },
    "21,29": {
      "weight": 6.24064833295358,
      "enabled": true
    },
    "0,36": {
      "weight": -1.4290727258858453,
      "enabled": true
    },
    "5,34": {
      "weight": -0.3910481404345483,
      "enabled": true
    },
    "1,39": {
      "weight": -0.07788285769999792,
      "enabled": false
    },
    "6,39": {
      "weight": -7.733244199211239,
      "enabled": true
    },
    "10,35": {
      "weight": -0.19058671380170766,
      "enabled": true
    },
    "15,29": {
      "weight": -0.45351917130167885,
      "enabled": true
    },
    "40,38": {
      "weight": 8.89759261811298,
      "enabled": true
    },
    "21,37": {
      "weight": 7.5184685662629,
      "enabled": true
    },
    "3,28": {
      "weight": -6.482421034042501,
      "enabled": true
    },
    "13,40": {
      "weight": 0.34036258117321494,
      "enabled": false
    },
    "41,31": {
      "weight": -9.129918968677508,
      "enabled": true
    },
    "1,41": {
      "weight": -0.5912392044546788,
      "enabled": true
    },
    "9,27": {
      "weight": -0.7146697462032838,
      "enabled": true
    },
    "26,29": {
      "weight": -7.13377199483336,
      "enabled": true
    },
    "16,28": {
      "weight": 3.8613435410288104,
      "enabled": true
    },
    "24,37": {
      "weight": -2.749960654039069,
      "enabled": false
    },
    "40,35": {
      "weight": 7.103683604422972,
      "enabled": true
    },
    "22,33": {
      "weight": 0.46242264098881813,
      "enabled": true
    },
    "22,36": {
      "weight": 0.0398230027235118,
      "enabled": true
    },
    "13,30": {
      "weight": -0.6929042340516842,
      "enabled": true
    },
    "8,35": {
      "weight": 9.071908688418238,
      "enabled": true
    },
    "4,34": {
      "weight": 7.280705147505984,
      "enabled": true
    },
    "12,37": {
      "weight": -0.8720632101169745,
      "enabled": true
    },
    "17,40": {
      "weight": -3.1729752752189895,
      "enabled": true
    },
    "12,40": {
      "weight": 0.3689598518234052,
      "enabled": true
    },
    "23,41": {
      "weight": 10.19463683173603,
      "enabled": true
    },
    "41,29": {
      "weight": -0.0828926013204776,
      "enabled": true
    },
    "5,40": {
      "weight": 0.7506964890722436,
      "enabled": true
    },
    "22,34": {
      "weight": -1.2374943110808416,
      "enabled": true
    },
    "6,32": {
      "weight": -7.745491931547779,
      "enabled": true
    },
    "0,42": {
      "weight": -1.581068688432092,
      "enabled": true
    },
    "42,36": {
      "weight": 4.024351885555494,
      "enabled": true
    },
    "22,38": {
      "weight": 5.340273923528761,
      "enabled": true
    },
    "4,28": {
      "weight": -4.389133052397107,
      "enabled": true
    },
    "41,30": {
      "weight": -0.20860924701442984,
      "enabled": true
    },
    "16,37": {
      "weight": -0.2169742389767464,
      "enabled": true
    },
    "12,38": {
      "weight": 0.4685303793585025,
      "enabled": true
    },
    "26,33": {
      "weight": -0.8552323495066911,
      "enabled": true
    },
    "20,37": {
      "weight": 0.511529372222602,
      "enabled": true
    },
    "1,38": {
      "weight": -0.03563683257086514,
      "enabled": true
    },
    "4,38": {
      "weight": 0.3354395690500598,
      "enabled": true
    },
    "2,32": {
      "weight": 1.0411489080089928,
      "enabled": true
    },
    "2,36": {
      "weight": -0.657953047411552,
      "enabled": true
    },
    "19,33": {
      "weight": 2.6412497729587896,
      "enabled": true
    },
    "15,32": {
      "weight": -0.8286702472643832,
      "enabled": true
    },
    "39,36": {
      "weight": -0.041166496150294885,
      "enabled": true
    },
    "9,36": {
      "weight": 0.5634100378586469,
      "enabled": true
    },
    "0,27": {
      "weight": -0.5646514760775143,
      "enabled": true
    },
    "4,41": {
      "weight": -0.5815371920276795,
      "enabled": true
    },
    "8,32": {
      "weight": -7.722935670016627,
      "enabled": true
    },
    "2,38": {
      "weight": 0.47526344701895407,
      "enabled": true
    },
    "12,32": {
      "weight": 0.32569772928727314,
      "enabled": true
    },
    "21,31": {
      "weight": -1.4283983920736423,
      "enabled": true
    },
    "8,33": {
      "weight": 0.8153043800721644,
      "enabled": true
    },
    "21,39": {
      "weight": -0.144002567069222,
      "enabled": true
    },
    "4,43": {
      "weight": 5.990615063460181,
      "enabled": true
    },
    "43,34": {
      "weight": 8.105105363155978,
      "enabled": false
    },
    "1,35": {
      "weight": 0.11310413710671274,
      "enabled": true
    },
    "43,41": {
      "weight": 8.664083834874226,
      "enabled": true
    },
    "26,45": {
      "weight": -2.405643827955929,
      "enabled": true
    },
    "45,30": {
      "weight": -7.257137046805515,
      "enabled": true
    },
    "42,38": {
      "weight": 0.4463922527945057,
      "enabled": true
    },
    "16,34": {
      "weight": -0.0681434369810685,
      "enabled": true
    },
    "43,28": {
      "weight": 0.046655306394757234,
      "enabled": true
    },
    "7,40": {
      "weight": -0.5969896598470279,
      "enabled": true
    },
    "23,30": {
      "weight": 0.249509117714535,
      "enabled": true
    },
    "3,45": {
      "weight": -0.5604201311592223,
      "enabled": true
    },
    "5,27": {
      "weight": -0.11643615905577986,
      "enabled": true
    },
    "4,46": {
      "weight": -0.5815371920276795,
      "enabled": true
    },
    "46,41": {
      "weight": 1.0,
      "enabled": true
    },
    "23,38": {
      "weight": 0.9249605802991818,
      "enabled": true
    },
    "18,45": {
      "weight": -7.3541136333333785,
      "enabled": true
    },
    "45,33": {
      "weight": 0.23106697151075806,
      "enabled": true
    },
    "46,39": {
      "weight": -0.18873929798274114,
      "enabled": true
    },
    "8,40": {
      "weight": -0.10589204709710898,
      "enabled": true
    },
    "15,30": {
      "weight": 0.9574061146690598,
      "enabled": true
    },
    "20,40": {
      "weight": -0.5948711205153305,
      "enabled": true
    },
    "24,32": {
      "weight": -0.39204665830721774,
      "enabled": true
    }
  },
  "id": 853786892
}